[
  {
    "timestamp": "2025-01-04T15:50:00.445Z",
    "status": "success",
    "table": "res_files",
    "message": "Successfully updated is_new field"
  },
  {
    "timestamp": "2025-01-04T15:51:01.029Z",
    "status": "success",
    "table": "res_folders",
    "message": "Successfully updated is_new field"
  },
  {
    "timestamp": "2025-01-04T15:51:01.065Z",
    "status": "success",
    "table": "res_files",
    "message": "Successfully updated is_new field"
  },
  {
    "timestamp": "2025-01-04T15:52:00.428Z",
    "status": "success",
    "table": "res_folders",
    "message": "Successfully updated is_new field"
  },
  {
    "timestamp": "2025-01-04T15:52:00.448Z",
    "status": "success",
    "table": "res_files",
    "message": "Successfully updated is_new field"
  },
  {
    "timestamp": "2025-01-04T15:53:01.008Z",
    "status": "success",
    "table": "res_folders",
    "message": "Successfully updated is_new field"
  },
  {
    "timestamp": "2025-01-04T15:53:01.045Z",
    "status": "success",
    "table": "res_files",
    "message": "Successfully updated is_new field"
  },
  {
    "timestamp": "2025-01-04T15:54:00.194Z",
    "status": "success",
    "table": "res_folders",
    "message": "Successfully updated is_new field"
  },
  {
    "timestamp": "2025-01-04T15:54:00.246Z",
    "status": "success",
    "table": "res_files",
    "message": "Successfully updated is_new field"
  },
  {
    "timestamp": "2025-01-04T16:20:00.909Z",
    "status": "success",
    "table": "res_folders",
    "message": "Successfully updated is_new field"
  },
  {
    "timestamp": "2025-01-04T16:20:00.924Z",
    "status": "success",
    "table": "res_files",
    "message": "Successfully updated is_new field"
  },
  {
    "timestamp": "2025-01-04T16:21:00.876Z",
    "status": "success",
    "table": "res_folders",
    "message": "Successfully updated is_new field"
  },
  {
    "timestamp": "2025-01-04T16:21:00.890Z",
    "status": "success",
    "table": "res_files",
    "message": "Successfully updated is_new field"
  }
]